aliyunsdkwebsitebuild/__init__.py
aliyunsdkwebsitebuild/request/__init__.py
aliyunsdkwebsitebuild/request/v20250429/BindAppDomainRequest.py
aliyunsdkwebsitebuild/request/v20250429/CreateLogoTaskRequest.py
aliyunsdkwebsitebuild/request/v20250429/DeleteAppDomainCertificateRequest.py
aliyunsdkwebsitebuild/request/v20250429/DeleteAppDomainRedirectRequest.py
aliyunsdkwebsitebuild/request/v20250429/DescribeAppDomainDnsRecordRequest.py
aliyunsdkwebsitebuild/request/v20250429/DispatchConsoleAPIForPartnerRequest.py
aliyunsdkwebsitebuild/request/v20250429/GetCreateLogoTaskRequest.py
aliyunsdkwebsitebuild/request/v20250429/GetDomainInfoForPartnerRequest.py
aliyunsdkwebsitebuild/request/v20250429/GetIcpFilingInfoForPartnerRequest.py
aliyunsdkwebsitebuild/request/v20250429/GetUserAccessTokenForPartnerRequest.py
aliyunsdkwebsitebuild/request/v20250429/GetUserTmpIdentityForPartnerRequest.py
aliyunsdkwebsitebuild/request/v20250429/ListAppDomainRedirectRecordsRequest.py
aliyunsdkwebsitebuild/request/v20250429/ListAppInstanceDomainsRequest.py
aliyunsdkwebsitebuild/request/v20250429/OperateAppInstanceForPartnerRequest.py
aliyunsdkwebsitebuild/request/v20250429/OperateAppServiceForPartnerRequest.py
aliyunsdkwebsitebuild/request/v20250429/SearchImageRequest.py
aliyunsdkwebsitebuild/request/v20250429/SetAppDomainCertificateRequest.py
aliyunsdkwebsitebuild/request/v20250429/SyncAppInstanceForPartnerRequest.py
aliyunsdkwebsitebuild/request/v20250429/UnbindAppDomainRequest.py
aliyunsdkwebsitebuild/request/v20250429/__init__.py
aliyun_python_sdk_websitebuild-1.0.8.dist-info/LICENSE
aliyun_python_sdk_websitebuild-1.0.8.dist-info/METADATA
aliyun_python_sdk_websitebuild-1.0.8.dist-info/WHEEL
aliyun_python_sdk_websitebuild-1.0.8.dist-info/top_level.txt
aliyun_python_sdk_websitebuild-1.0.8.dist-info/RECORD
